F_Funtion/__init__.py
F_Funtion/ffunction.py
F_Funtion-0.0.1.dist-info/METADATA
F_Funtion-0.0.1.dist-info/WHEEL
F_Funtion-0.0.1.dist-info/top_level.txt
F_Funtion-0.0.1.dist-info/RECORD
