Metadata-Version: 2.1
Name: F-Funtion
Version: 0.0.1
Summary: Simple test example
Author: xiao_gao
Author-email: 1752420742@qq.com
Classifier: Programming Language :: Python :: 3
Classifier: License :: OSI Approved :: MIT License
Classifier: Operating System :: OS Independent
Requires-Python: >=3.6
